{
  "date": "2026-04-03",
  "generated_at": "2026-04-03T13:37:00Z",
  "period": "Ultimas 24h (2026-04-02 13:37 - 2026-04-03 13:37 UTC)",
  "agents": {
    "UX/UINightShiftAgent": [
      {
        "start": "2026-04-02T23:08:00Z",
        "end": "2026-04-03T00:38:00Z",
        "duration_min": 90,
        "task": "UX/UI Review - Mobile improvements, accessibility, performance",
        "priority": "P0",
        "details": [
          "Fix: Mobile sidebar swipe gestures",
          "Fix: Color contrast accessibility (WCAG AA)",
          "Fix: Preconnect for external resources (Performance +200-300ms LCP)",
          "Feat: Pull-to-refresh implementation",
          "Feat: Toast notifications system",
          "Feat: Bottom navigation for mobile",
          "Feat: Illustrated empty states",
          "Feat: Focus states improved"
        ],
        "evidence_link": "/evidencias/20260402/uxui_review_0708.md",
        "files_modified": ["control-plane/public/dashboard.html"],
        "metrics_impact": {
          "LCP_Mobile": "-12%",
          "CLS_Mobile": "-67%",
          "Accessibility_Lighthouse": "+22pts"
        }
      },
      {
        "start": "2026-04-03T05:10:00Z",
        "end": "2026-04-03T06:40:00Z",
        "duration_min": 90,
        "task": "UX/UI Review v2 - Design System Refinement",
        "priority": "P0",
        "details": [
          "Fix: Color contrast on metric values (removed gradient)",
          "Fix: Sidebar navigation feedback consistency",
          "Feat: Trend indicators styling improved",
          "Feat: Standardized status badges system",
          "Feat: Enhanced swipe indicator visibility",
          "Feat: Card hover effects with shadows"
        ],
        "evidence_link": "/evidencias/20260403/uxui_review_0210.md",
        "files_modified": [
          "control-plane/public/dashboard.html",
          "control-plane/public/css/criativalia-theme.css"
        ]
      }
    ],
    "DesignBot": [
      {
        "start": "2026-04-03T04:42:00Z",
        "end": "2026-04-03T05:22:00Z",
        "duration_min": 40,
        "task": "Design System Implementation - Criativalia Theme",
        "priority": "P1",
        "details": [
          "Created: criativalia-theme.css with CSS variables",
          "Created: index.html design system showcase",
          "Components: Cards (3 variants)",
          "Components: Buttons (5 variants + 3 sizes)",
          "Components: Form inputs, Select, Textarea",
          "Components: Navigation, Badges, Stats cards",
          "Design tokens: Colors, Typography, Spacing, Shadows"
        ],
        "evidence_link": "/evidencias/20260403/design_update_0442.md",
        "files_modified": [
          "criativalia-theme.css",
          "index.html"
        ],
        "theme": {
          "primary": "#4A5D23",
          "secondary": "#F5F5DC",
          "style": "Olive Green + Off-White"
        }
      },
      {
        "start": "2026-04-03T05:08:00Z",
        "end": "2026-04-03T06:08:00Z",
        "duration_min": 60,
        "task": "Design System Refinement v2.1",
        "priority": "P1",
        "details": [
          "Created: Criativalia logo SVG (200x60px)",
          "Refined: Complete olive green color palette",
          "Updated: All component styles consistent",
          "Added: Navbar with logo integration",
          "Verified: Responsiveness mobile (768px)"
        ],
        "evidence_link": "/evidencias/20260403/design_update_0508.md",
        "files_modified": [
          "public/css/criativalia-theme.css",
          "public/index.html",
          "public/images/criativalia-logo.svg"
        ]
      }
    ],
    "TrafficBot": [],
    "CopyBot": [],
    "OpsBot": []
  },
  "summary": {
    "total_activities": 4,
    "total_hours": 4.67,
    "agents_active": 2,
    "p0_tasks": 2,
    "p1_tasks": 2,
    "files_modified": 5
  }
}